cy_components/CYComponents.py
cy_components/__init__.py
cy_components/defines/__init__.py
cy_components/defines/column_names.py
cy_components/defines/enums.py
cy_components/helpers/__init__.py
cy_components/helpers/formatter.py
cy_components/utils/__init__.py
cy_components/utils/coin_pair.py
cy_components/utils/functions.py
cy_components/utils/notifier.py
cy_components/utils/one_token.py
cy_components-0.3.18.dist-info/LICENSE
cy_components-0.3.18.dist-info/METADATA
cy_components-0.3.18.dist-info/WHEEL
cy_components-0.3.18.dist-info/top_level.txt
cy_components-0.3.18.dist-info/RECORD
