Metadata-Version: 2.1
Name: cy-components
Version: 0.3.18
Summary: Infrastructure of quan app
Home-page: https://github.com/cragod/CYComponents
Author: Gatro CY
Author-email: cragodn@gmail.com
License: MIT license
Keywords: cy_components
Platform: UNKNOWN
Classifier: Development Status :: 2 - Pre-Alpha
Classifier: Intended Audience :: Developers
Classifier: License :: OSI Approved :: MIT License
Classifier: Natural Language :: English
Classifier: Programming Language :: Python :: 3
Classifier: Programming Language :: Python :: 3.5
Classifier: Programming Language :: Python :: 3.6
Classifier: Programming Language :: Python :: 3.7
Classifier: Programming Language :: Python :: 3.8
Requires-Python: >=3.7
License-File: LICENSE
Requires-Dist: pandas (>=1.1.5)
Requires-Dist: pyyaml (>=5.4.1)
